{
  "appKey": "",
  "appSecret": "",
  "encryptJs": true,
  "excludeScenes": [],
  "fb-instant-games": {},
  "includeAnySDK": false,
  "includeSDKBox": false,
  "inlineSpriteFrames": true,
  "inlineSpriteFrames_native": true,
  "jailbreakPlatform": false,
  "md5Cache": true,
  "mergeStartScene": false,
  "oauthLoginServer": "",
  "optimizeHotUpdate": false,
  "orientation": {
    "landscapeLeft": true,
    "landscapeRight": true,
    "portrait": false,
    "upsideDown": false
  },
  "packageName": "org.cocos2d.PartyGame",
  "privateKey": "",
  "qqplay": {
    "REMOTE_SERVER_ROOT": "",
    "orientation": "portrait"
  },
  "renderMode": "0",
  "startScene": "09526874-df96-466b-91cc-fdddfea672b5",
  "title": "PartyGame",
  "webOrientation": "auto",
  "wechatgame": {
    "REMOTE_SERVER_ROOT": "",
    "appid": "wx7fe693460c53aefe",
    "isSubdomain": false,
    "orientation": "landscape",
    "subContext": ""
  },
  "xxteaKey": "19fa2d77-f566-44",
  "zipCompressJs": true
}